{
  "template_version": 3,
  "source_type": "excel",
  "sheet": "messy",
  "sheets": [],
  "header_row": 1,
  "skiprows": [],
  "delimiter": ",",
  "encoding": "utf-8",
  "columns": [],
  "column_mappings": {},
  "headers": [
    {
      "name": "Sales Report Q1",
      "column": 0,
      "row": 0,
      "is_metadata": true,
      "metadata_type": "metadata"
    },
    {
      "name": "Product Code",
      "column": 1,
      "row": 1,
      "is_metadata": true,
      "metadata_type": "metadata"
    },
    {
      "name": "Qty",
      "column": 2,
      "row": 1,
      "is_metadata": true,
      "metadata_type": "metadata"
    },
    {
      "name": "Amount",
      "column": 3,
      "row": 1,
      "is_metadata": true,
      "metadata_type": "metadata"
    }
  ],
  "source_file": "sample_messy.xlsx",
  "output_dir": null,
  "provider_name": null,
  "combine_sheets": false,
  "combine_on": [],
  "connection_name": null,
  "trim_strings": true,
  "drop_empty_rows": false,
  "drop_null_columns_threshold": null,
  "dedupe_on": [],
  "strip_thousands": false,
  "sql_table": null,
  "sql_query": null,
  "unpivot": false,
  "id_columns": [],
  "var_name": "report_date",
  "value_name": "sales_amount",
  "required_fields": [],
  "field_types": {}
}